musicgen_trainer/__init__.py
musicgen_trainer/musicgen_trainer.py
musicgen_trainer-1.0.1.dist-info/METADATA
musicgen_trainer-1.0.1.dist-info/WHEEL
musicgen_trainer-1.0.1.dist-info/top_level.txt
musicgen_trainer-1.0.1.dist-info/RECORD
